tendrils/__init__.py
tendrils/version.py
tendrils/api/__init__.py
tendrils/api/catalogs.py
tendrils/api/datafiles.py
tendrils/api/filters.py
tendrils/api/lightcurves.py
tendrils/api/photometry_api.py
tendrils/api/set_photometry_status.py
tendrils/api/sites.py
tendrils/api/targets.py
tendrils/utils/__init__.py
tendrils/utils/config.ini
tendrils/utils/config.py
tendrils/utils/files.py
tendrils/utils/time.py
tendrils/utils/tns.py
tendrils/utils/urls.py
tendrils/utils/ztf.py
tendrils-0.3.2.dist-info/LICENSE.rst
tendrils-0.3.2.dist-info/WHEEL
tendrils-0.3.2.dist-info/METADATA
tendrils-0.3.2.dist-info/RECORD
